Metadata-Version: 2.1
Name: supermeter-autowrapt
Version: 1.1.6
Summary: Boostrap mechanism for monkey patches for supermeter.
Home-page: https://github.com/supertenant/supermeter-autowrapt
Author: SuperTenant Ltd.
Author-email: info@supertenant.com
License: BSD
License-File: LICENSE
Requires-Dist: wrapt>=1.10.4
